tb_ioc/__init__.py
tb_ioc/class_utils.py
tb_ioc/exception.py
tb_ioc/factory.py
tb_ioc/model.py
tb_ioc-0.3.5.dist-info/DESCRIPTION.rst
tb_ioc-0.3.5.dist-info/METADATA
tb_ioc-0.3.5.dist-info/RECORD
tb_ioc-0.3.5.dist-info/WHEEL
tb_ioc-0.3.5.dist-info/metadata.json
tb_ioc-0.3.5.dist-info/top_level.txt
