Metadata-Version: 2.0
Name: tb-ioc
Version: 0.3.5
Summary: IOC (Inversion of control) for Python
Home-page: https://github.com/thongdong7/tb-ioc
Author: Thong Dong
Author-email: thongdong7@gmail.com
License: UNKNOWN
Platform: UNKNOWN
Requires-Dist: pyyaml (~=3.11)
Requires-Dist: six (~=1.10)
Requires-Dist: future
